MANIFEST.in
README.rst
setup.py
pyCLAWSps/__init__.py
pyCLAWSps.egg-info/PKG-INFO
pyCLAWSps.egg-info/SOURCES.txt
pyCLAWSps.egg-info/dependency_links.txt
pyCLAWSps.egg-info/not-zip-safe
pyCLAWSps.egg-info/requires.txt
pyCLAWSps.egg-info/top_level.txt