Metadata-Version: 1.1
Name: pyCLAWSps
Version: 0.1.10
Summary: Python Code for Power Supply Hamamatsu c11204-01/02
Home-page: https://github.com/malindasds/pyCLAWSps
Author: Malinda de Silva
Author-email: desilva@mpp.mpg.de
License: gpl-3.0
Keywords: python hamamatsu power supply c11204
Platform: UNKNOWN
Classifier: Programming Language :: Python :: 3
Classifier: License :: OSI Approved :: GNU General Public License v3 (GPLv3)
Classifier: Operating System :: OS Independent
